[
    {
        "name": "Frank",
        "id": "30584",
        "type": "OAV",
        "vintage": "2005-11"
    },
    {
        "name": "Hi-Rise Hopper",
        "id": "30579",
        "type": "OAV",
        "vintage": "2005-11"
    },
    {
        "name": "Frank",
        "id": "30577",
        "type": "OAV",
        "vintage": "2005-11"
    },
    {
        "name": "Dore Dore no Uta",
        "id": "10078",
        "type": "special",
        "vintage": "2005-11"
    },
    {
        "name": "Onna Ky\u014dshi: Nikutai Jugy\u014d",
        "id": "9319",
        "type": "OAV",
        "vintage": "2005-12"
    },
    {
        "name": "Night Shift Nurse: Ren Nanase",
        "id": "8185",
        "type": "OAV",
        "vintage": "2005-12"
    },
    {
        "name": "Nee, Chanto Shiy\u014d yo!",
        "id": "7691",
        "type": "OAV",
        "vintage": "2005-11"
    },
    {
        "name": "Virgin Auction",
        "id": "7366",
        "type": "OAV",
        "vintage": "2005-12"
    },
    {
        "name": "Hills Have Size",
        "id": "7226",
        "type": "OAV",
        "vintage": "2005-12"
    },
    {
        "name": "Cambrian",
        "id": "7069",
        "type": "OAV",
        "vintage": "2005-11"
    },
    {
        "name": "True Blue Gaiden",
        "id": "7068",
        "type": "OAV",
        "vintage": "2005-12"
    },
    {
        "name": "Innocent Blue",
        "id": "7066",
        "type": "OAV",
        "vintage": "2005-11"
    },
    {
        "name": "It's a Family Affair",
        "id": "6994",
        "type": "OAV",
        "vintage": "2005-12"
    },
    {
        "name": "Spa of Love",
        "id": "6992",
        "type": "OAV",
        "vintage": "2005-10"
    },
    {
        "name": "Insatiable",
        "id": "6981",
        "type": "OAV",
        "vintage": "2005-12"
    },
    {
        "name": "MegaMan Maverick Hunter X: The Day of Sigma",
        "id": "6980",
        "type": "OAV",
        "vintage": "2005-12"
    },
    {
        "name": "Rebirth Moon Divergence",
        "id": "6949",
        "type": "OAV",
        "vintage": "2005-11"
    },
    {
        "name": "Saint Beast ~Ikusen no Hiru to Yoru Hen~",
        "id": "6937",
        "type": "OAV",
        "vintage": "2005-12"
    },
    {
        "name": "Harukanaru Toki no Naka de: Hachiy\u014d Sh\u014d",
        "id": "6901",
        "type": "OAV",
        "vintage": "2005-12"
    },
    {
        "name": "Minami no Shima no Chiisana Hikouki Birdy",
        "id": "6883",
        "type": "TV",
        "vintage": "2005-12"
    },
    {
        "name": "Hininden Gausu",
        "id": "6584",
        "type": "OAV",
        "vintage": "2005-12"
    },
    {
        "name": "Maid in Heaven",
        "id": "6510",
        "type": "OAV",
        "vintage": "2005-10"
    },
    {
        "name": "Idaten Jump",
        "id": "6495",
        "type": "TV",
        "vintage": "2005-10"
    },
    {
        "name": "Kiss in the Dark",
        "id": "6353",
        "type": "OAV",
        "vintage": "2005-11"
    },
    {
        "name": "Kotenkotenko",
        "id": "6351",
        "type": "TV",
        "vintage": "2005-10"
    },
    {
        "name": "Fighting Beauty Wulong",
        "id": "6347",
        "type": "TV",
        "vintage": "2005-10"
    },
    {
        "name": "Rockman.EXE Beast",
        "id": "6313",
        "type": "TV",
        "vintage": "2005-10"
    },
    {
        "name": "Tohai Densetu Akagi -Yamini Maiorita Tensai-",
        "id": "6294",
        "type": "TV",
        "vintage": "2005-10"
    },
    {
        "name": "Dr. Pinoko no Mori no B\u014dken",
        "id": "6242",
        "type": "movie",
        "vintage": "2005-12"
    },
    {
        "name": "Beet the Vandel Buster Excellion",
        "id": "6209",
        "type": "TV",
        "vintage": "2005-10"
    },
    {
        "name": "Kouchuu Ouja Mushiking: Greatest Champion e no Michi",
        "id": "6162",
        "type": "movie",
        "vintage": "2005-12"
    },
    {
        "name": "Capeta",
        "id": "6138",
        "type": "TV",
        "vintage": "2005-10"
    },
    {
        "name": "Kaleido Star: Legend of Phoenix - Layla Hamilton Story",
        "id": "6075",
        "type": "OAV",
        "vintage": "2005-12"
    },
    {
        "name": "Naruto",
        "id": "6057",
        "type": "OAV",
        "vintage": "2005-12"
    },
    {
        "name": "Ginban Kaleidoscope",
        "id": "6050",
        "type": "TV",
        "vintage": "2005-10"
    },
    {
        "name": "Mother Knows Breast",
        "id": "6037",
        "type": "OAV",
        "vintage": "2005-10"
    },
    {
        "name": "Itsudatte My Santa!",
        "id": "5979",
        "type": "OAV",
        "vintage": "2005-12"
    },
    {
        "name": "Canvas 2 - Niji Iro no Sketch",
        "id": "5976",
        "type": "TV",
        "vintage": "2005-10"
    },
    {
        "name": "Mobile Suit Gundam Seed Destiny Final Plus: The Chosen Future",
        "id": "5965",
        "type": "OAV",
        "vintage": "2005-12"
    },
    {
        "name": "Saint Seiya: The Hades Chapter - Inferno",
        "id": "5964",
        "type": "OAV",
        "vintage": "2005-12"
    },
    {
        "name": "School Rumble: Extra Class",
        "id": "5957",
        "type": "OAV",
        "vintage": "2005-12"
    },
    {
        "name": "Wings of Rean",
        "id": "5950",
        "type": "ONA",
        "vintage": "2005-12"
    },
    {
        "name": "Karin",
        "id": "5949",
        "type": "TV",
        "vintage": "2005-11"
    },
    {
        "name": "King of Fighters: Another Day",
        "id": "5924",
        "type": "ONA",
        "vintage": "2005-12"
    },
    {
        "name": "Mushi-Shi",
        "id": "5923",
        "type": "TV",
        "vintage": "2005-10"
    },
    {
        "name": "Arashi no Yoru ni",
        "id": "5905",
        "type": "movie",
        "vintage": "2005-12"
    },
    {
        "name": "I''s Pure",
        "id": "5896",
        "type": "OAV",
        "vintage": "2005-11"
    },
    {
        "name": "Gaiking: Legend of Daik\u016b-mary\u016b",
        "id": "5894",
        "type": "TV",
        "vintage": "2005-11"
    },
    {
        "name": "Noein - to your other self",
        "id": "5887",
        "type": "TV",
        "vintage": "2005-10"
    },
    {
        "name": "Happy Seven",
        "id": "5870",
        "type": "TV",
        "vintage": "2005-10"
    },
    {
        "name": "Lamune",
        "id": "5868",
        "type": "TV",
        "vintage": "2005-10"
    },
    {
        "name": "Immortal Grand Prix",
        "id": "5862",
        "type": "TV",
        "vintage": "2005-10"
    },
    {
        "name": "Black Jack: The Two Doctors Of Darkness",
        "id": "5861",
        "type": "movie",
        "vintage": "2005-12"
    },
    {
        "name": "Gunparade Orchestra",
        "id": "5822",
        "type": "TV",
        "vintage": "2005-10"
    },
    {
        "name": "ToHeart2",
        "id": "5821",
        "type": "TV",
        "vintage": "2005-10"
    },
    {
        "name": "Futari wa Precure Max Heart 2: Yukizora no Tomodachi",
        "id": "5797",
        "type": "movie",
        "vintage": "2005-12"
    },
    {
        "name": "Animal Yokocho",
        "id": "5793",
        "type": "TV",
        "vintage": "2005-10"
    },
    {
        "name": "Magical Girl Lyrical Nanoha A's",
        "id": "5770",
        "type": "TV",
        "vintage": "2005-10"
    },
    {
        "name": "Hell Girl",
        "id": "5577",
        "type": "TV",
        "vintage": "2005-10"
    },
    {
        "name": "Aria the Animation",
        "id": "5504",
        "type": "TV",
        "vintage": "2005-10"
    },
    {
        "name": "Angel Heart",
        "id": "5487",
        "type": "TV",
        "vintage": "2005-10"
    },
    {
        "name": "Fate/stay night",
        "id": "5394",
        "type": "TV",
        "vintage": "2005-11"
    },
    {
        "name": "My-Otome",
        "id": "5378",
        "type": "TV",
        "vintage": "2005-10"
    },
    {
        "name": "Fafner in the Azure - Right of Left",
        "id": "5251",
        "type": "special",
        "vintage": "2005-12"
    },
    {
        "name": "Black Cat",
        "id": "5245",
        "type": "TV",
        "vintage": "2005-10"
    },
    {
        "name": "Blood+",
        "id": "5088",
        "type": "TV",
        "vintage": "2005-10"
    },
    {
        "name": "Rozen Maiden: Tr\u00e4umend",
        "id": "5087",
        "type": "TV",
        "vintage": "2005-10"
    },
    {
        "name": "Paradise Kiss",
        "id": "5081",
        "type": "TV",
        "vintage": "2005-10"
    },
    {
        "name": "Solty Rei",
        "id": "5051",
        "type": "TV",
        "vintage": "2005-10"
    },
    {
        "name": "Cluster Edge",
        "id": "4671",
        "type": "TV",
        "vintage": "2005-10"
    },
    {
        "name": "Street Fighter Alpha: Generations",
        "id": "2759",
        "type": "OAV",
        "vintage": "2005-10"
    }
]