[
    {
        "name": "Anata ga Furikaeru Toki",
        "id": "23393",
        "type": "OAV",
        "vintage": "1993-03"
    },
    {
        "name": "Kero Kero Keroppi no Mitsubachi Dais\u014dd\u014d",
        "id": "23146",
        "type": "OAV",
        "vintage": "1993-03"
    },
    {
        "name": "Kero Kero Keroppi no Tomodachi wa Mah\u014d Tsukai",
        "id": "23136",
        "type": "OAV",
        "vintage": "1993-02"
    },
    {
        "name": "Kappa no Sanpei",
        "id": "22334",
        "type": "movie",
        "vintage": "1993-03"
    },
    {
        "name": "Zoku Kuronekoyakata",
        "id": "17079",
        "type": "OAV",
        "vintage": "1993-03"
    },
    {
        "name": "Ganbare Goemon: Jigen Jou no Akumu",
        "id": "16268",
        "type": "OAV",
        "vintage": "1993-03"
    },
    {
        "name": "Offside",
        "id": "10152",
        "type": "OAV",
        "vintage": "1993-01"
    },
    {
        "name": "Columbus's Great Adventures",
        "id": "4405",
        "type": "OAV",
        "vintage": "1993-01"
    },
    {
        "name": "Mobile Suit SD Gundam Festival",
        "id": "4150",
        "type": "movie",
        "vintage": "1993-03"
    },
    {
        "name": "Armored Dragon Legend Villgust",
        "id": "4135",
        "type": "OAV",
        "vintage": "1993-01"
    },
    {
        "name": "Sangokushi [2] Ch\u014dk\u014d Moyu!",
        "id": "3855",
        "type": "movie",
        "vintage": "1993-03"
    },
    {
        "name": "Kamen Rider SD",
        "id": "3810",
        "type": "OAV",
        "vintage": "1993-01"
    },
    {
        "name": "Dr. Slump & Arale-chan Ncha! Penguin Mura wa Hare no chi Hare",
        "id": "3692",
        "type": "movie",
        "vintage": "1993-03"
    },
    {
        "name": "Aru Kararu no Isan",
        "id": "2312",
        "type": "OAV",
        "vintage": "1993-01"
    },
    {
        "name": "Nekketsu Saikyo Gozaurer",
        "id": "2236",
        "type": "TV",
        "vintage": "1993-03"
    },
    {
        "name": "Little Women II Jo's Boys",
        "id": "2078",
        "type": "TV",
        "vintage": "1993-01"
    },
    {
        "name": "Brave Express Might Gaine",
        "id": "1957",
        "type": "TV",
        "vintage": "1993-01"
    },
    {
        "name": "Dorami-chan: Hello, Dynosis Kids!!",
        "id": "1933",
        "type": "movie",
        "vintage": "1993-03"
    },
    {
        "name": "Doraemon the Movie: Nobita and the Tin Labyrinth",
        "id": "1908",
        "type": "movie",
        "vintage": "1993-03"
    },
    {
        "name": "Dragon Ball Z: Broly - The Legendary Super Saiyan",
        "id": "986",
        "type": "movie",
        "vintage": "1993-03"
    },
    {
        "name": "Ambassador Magma",
        "id": "929",
        "type": "OAV",
        "vintage": "1993-02"
    },
    {
        "name": "Miracle Girls",
        "id": "808",
        "type": "TV",
        "vintage": "1993-01"
    },
    {
        "name": "Moldiver",
        "id": "699",
        "type": "OAV",
        "vintage": "1993-02"
    },
    {
        "name": "Dragon Half",
        "id": "542",
        "type": "OAV",
        "vintage": "1993-03"
    },
    {
        "name": "Sailor Moon R",
        "id": "213",
        "type": "TV",
        "vintage": "1993-03"
    },
    {
        "name": "Irresponsible Captain Tylor",
        "id": "160",
        "type": "TV",
        "vintage": "1993-01"
    },
    {
        "name": "Dragon Ball Z: The History of Trunks",
        "id": "133",
        "type": "special",
        "vintage": "1993-02"
    },
    {
        "name": "Kishin Corps",
        "id": "35",
        "type": "OAV",
        "vintage": "1993-03"
    }
]