[
    {
        "name": "Kero Kero Keroppi no Aladdin to Mah\u014d no Lamp",
        "id": "23140",
        "type": "OAV",
        "vintage": "2001-11"
    },
    {
        "name": "Ko Ko Ro",
        "id": "15369",
        "type": "OAV",
        "vintage": "2001-12"
    },
    {
        "name": "My Honny is College School Gal",
        "id": "15262",
        "type": "OAV",
        "vintage": "2001-12"
    },
    {
        "name": "Please Save My Earth Music Image Video: Kin-Iro no Toki Nagarete",
        "id": "10144",
        "type": "special",
        "vintage": "2001-10"
    },
    {
        "name": "Karakara-sama no Himitsu - Ten kara kita Megami",
        "id": "9755",
        "type": "OAV",
        "vintage": "2001-11"
    },
    {
        "name": "Prima Donna Mai",
        "id": "9681",
        "type": "OAV",
        "vintage": "2001-12"
    },
    {
        "name": "Girl's Locker Room Lust",
        "id": "9680",
        "type": "OAV",
        "vintage": "2001-12"
    },
    {
        "name": "SM no Susume",
        "id": "9311",
        "type": "OAV",
        "vintage": "2001-10"
    },
    {
        "name": "University Girls",
        "id": "8791",
        "type": "OAV",
        "vintage": "2001-12"
    },
    {
        "name": "Be Lifesized My Lover - Mechanic Minami vs. Human Minami",
        "id": "7834",
        "type": "OAV",
        "vintage": "2001-10"
    },
    {
        "name": "Zero no Mono",
        "id": "7829",
        "type": "OAV",
        "vintage": "2001-10"
    },
    {
        "name": "Sin Sorority",
        "id": "7364",
        "type": "OAV",
        "vintage": "2001-10"
    },
    {
        "name": "Countdown to Delight",
        "id": "7218",
        "type": "OAV",
        "vintage": "2001-10"
    },
    {
        "name": "Kanzen Shouri Daiteioh",
        "id": "7157",
        "type": "OAV",
        "vintage": "2001-12"
    },
    {
        "name": "Mahya the Servant",
        "id": "7043",
        "type": "OAV",
        "vintage": "2001-12"
    },
    {
        "name": "Marine a Go Go",
        "id": "6454",
        "type": "OAV",
        "vintage": "2001-12"
    },
    {
        "name": "Midnight Strike Force",
        "id": "6217",
        "type": "OAV",
        "vintage": "2001-11"
    },
    {
        "name": "Zero Sum Game",
        "id": "5037",
        "type": "OAV",
        "vintage": "2001-10"
    },
    {
        "name": "Zoku Koihime",
        "id": "4931",
        "type": "OAV",
        "vintage": "2001-11"
    },
    {
        "name": "I Love You",
        "id": "4720",
        "type": "OAV",
        "vintage": "2001-12"
    },
    {
        "name": "Hooligan",
        "id": "4406",
        "type": "OAV",
        "vintage": "2001-11"
    },
    {
        "name": "Stepmother's Sin",
        "id": "4329",
        "type": "OAV",
        "vintage": "2001-10"
    },
    {
        "name": "F-Force",
        "id": "4034",
        "type": "OAV",
        "vintage": "2001-10"
    },
    {
        "name": "Geisters - Fractions of the Earth",
        "id": "3919",
        "type": "TV",
        "vintage": "2001-10"
    },
    {
        "name": "Natural Obsessions 2",
        "id": "3155",
        "type": "OAV",
        "vintage": "2001-11"
    },
    {
        "name": "Gundam Evolve",
        "id": "2980",
        "type": "OAV",
        "vintage": "2001-11"
    },
    {
        "name": "Vandread Integral",
        "id": "2937",
        "type": "OAV",
        "vintage": "2001-12"
    },
    {
        "name": "Moonlight Lady",
        "id": "2709",
        "type": "OAV",
        "vintage": "2001-12"
    },
    {
        "name": "Angel Blade",
        "id": "2601",
        "type": "OAV",
        "vintage": "2001-12"
    },
    {
        "name": "Vampiyan Kids",
        "id": "2479",
        "type": "TV",
        "vintage": "2001-10"
    },
    {
        "name": "Legend of the Condor Hero",
        "id": "2274",
        "type": "TV",
        "vintage": "2001-10"
    },
    {
        "name": "Pocket Monster Crystal: Raikou Ikazuchi no Densetsu",
        "id": "2268",
        "type": "special",
        "vintage": "2001-12"
    },
    {
        "name": "Azumanga Daioh - The Very Short Movie",
        "id": "2258",
        "type": "movie",
        "vintage": "2001-12"
    },
    {
        "name": "Gekito! Crush Gear Turbo",
        "id": "2169",
        "type": "TV",
        "vintage": "2001-10"
    },
    {
        "name": "Canvas - Sepia-iro no Motif",
        "id": "2105",
        "type": "OAV",
        "vintage": "2001-12"
    },
    {
        "name": "Yobarete Tobidete Akubi-chan",
        "id": "2080",
        "type": "TV",
        "vintage": "2001-12"
    },
    {
        "name": "Kaze no Yojimbo",
        "id": "1809",
        "type": "TV",
        "vintage": "2001-10"
    },
    {
        "name": "Rave Master",
        "id": "1784",
        "type": "TV",
        "vintage": "2001-10"
    },
    {
        "name": "Kogepan",
        "id": "1653",
        "type": "TV",
        "vintage": "2001-11"
    },
    {
        "name": "Shiawase Sou no Okojo-san",
        "id": "1535",
        "type": "TV",
        "vintage": "2001-10"
    },
    {
        "name": "Tottoko Hamutar\u014d: Hamu Hamu Land Daib\u014dken",
        "id": "1518",
        "type": "movie",
        "vintage": "2001-12"
    },
    {
        "name": "Kirby: Right Back At Ya!",
        "id": "1394",
        "type": "TV",
        "vintage": "2001-10"
    },
    {
        "name": "Fighting Foodons",
        "id": "1371",
        "type": "TV",
        "vintage": "2001-12"
    },
    {
        "name": "3D Magical Play",
        "id": "1349",
        "type": "OAV",
        "vintage": "2001-12"
    },
    {
        "name": "Project ARMS: The 2nd Chapter",
        "id": "1348",
        "type": "TV",
        "vintage": "2001-10"
    },
    {
        "name": "Cyborg 009 The Cyborg Soldier",
        "id": "1288",
        "type": "TV",
        "vintage": "2001-10"
    },
    {
        "name": "Angel Tales",
        "id": "1196",
        "type": "TV",
        "vintage": "2001-10"
    },
    {
        "name": "Baboo Factory",
        "id": "1193",
        "type": "TV",
        "vintage": "2001-10"
    },
    {
        "name": "Captain Tsubasa: Road to 2002",
        "id": "1145",
        "type": "TV",
        "vintage": "2001-10"
    },
    {
        "name": "Memories Off",
        "id": "1138",
        "type": "OAV",
        "vintage": "2001-11"
    },
    {
        "name": "Kokoro Library",
        "id": "1119",
        "type": "TV",
        "vintage": "2001-10"
    },
    {
        "name": "Little Snow Fairy Sugar",
        "id": "1018",
        "type": "TV",
        "vintage": "2001-10"
    },
    {
        "name": "Fushigi Yugi Eikoden",
        "id": "967",
        "type": "OAV",
        "vintage": "2001-12"
    },
    {
        "name": "Hikaru no Go",
        "id": "912",
        "type": "TV",
        "vintage": "2001-10"
    },
    {
        "name": "Prince of Tennis",
        "id": "876",
        "type": "TV",
        "vintage": "2001-10"
    },
    {
        "name": "Zaion: I Wish You Were Here",
        "id": "845",
        "type": "ONA",
        "vintage": "2001-10"
    },
    {
        "name": "Patlabor WXIII",
        "id": "660",
        "type": "movie",
        "vintage": "2001-12"
    },
    {
        "name": "Final Fantasy: Unlimited",
        "id": "639",
        "type": "TV",
        "vintage": "2001-10"
    },
    {
        "name": "Stray Sheep",
        "id": "604",
        "type": "TV",
        "vintage": "2001-10"
    },
    {
        "name": "Vandread: The Second Stage",
        "id": "601",
        "type": "TV",
        "vintage": "2001-10"
    },
    {
        "name": "Kikaider-01: The Animation",
        "id": "494",
        "type": "OAV",
        "vintage": "2001-11"
    },
    {
        "name": "Babel II - Beyond Infinity",
        "id": "490",
        "type": "TV",
        "vintage": "2001-10"
    },
    {
        "name": "X",
        "id": "464",
        "type": "TV",
        "vintage": "2001-10"
    },
    {
        "name": "Mahoromatic - Automatic Maiden",
        "id": "428",
        "type": "TV",
        "vintage": "2001-10"
    },
    {
        "name": "Najica Blitz Tactics",
        "id": "420",
        "type": "TV",
        "vintage": "2001-10"
    },
    {
        "name": "Hellsing",
        "id": "387",
        "type": "TV",
        "vintage": "2001-10"
    },
    {
        "name": "Please Teacher!",
        "id": "386",
        "type": "TV",
        "vintage": "2001-12"
    },
    {
        "name": "Kuru Kuru Amy",
        "id": "341",
        "type": "TV",
        "vintage": "2001-10"
    },
    {
        "name": "Rurouni Kenshin: Reflection",
        "id": "310",
        "type": "OAV",
        "vintage": "2001-12"
    },
    {
        "name": "Kai Doh Maru",
        "id": "306",
        "type": "OAV",
        "vintage": "2001-12"
    },
    {
        "name": "Magical Play",
        "id": "305",
        "type": "ONA",
        "vintage": "2001-10"
    },
    {
        "name": "Sakura Wars: The Movie",
        "id": "296",
        "type": "movie",
        "vintage": "2001-12"
    },
    {
        "name": "Slayers Premium",
        "id": "295",
        "type": "movie",
        "vintage": "2001-12"
    },
    {
        "name": "InuYasha the Movie: Affections Touching Across Time",
        "id": "294",
        "type": "movie",
        "vintage": "2001-12"
    },
    {
        "name": "Kasumin",
        "id": "205",
        "type": "TV",
        "vintage": "2001-10"
    }
]